docker_captain/__init__.py
docker_captain/config.py
docker_captain/docker.py
docker_captain/main.py
docker_captain/projects.py
docker_captain-0.1.5.dist-info/licenses/LICENSE
docker_captain-0.1.5.dist-info/WHEEL
docker_captain-0.1.5.dist-info/entry_points.txt
docker_captain-0.1.5.dist-info/METADATA
docker_captain-0.1.5.dist-info/RECORD
