Metadata-Version: 2.4
Name: docker-captain
Version: 0.1.5
Summary: A friendly CLI to manage multiple Docker Compose deployments with style.
Author: Luca Bello
Author-email: Luca Bello <lusgabello@gmail.com>
License-Expression: Apache-2.0
License-File: LICENSE
Requires-Dist: platformdirs>=4.5.0
Requires-Dist: pyyaml>=6.0.3
Requires-Dist: questionary>=2.1.1
Requires-Dist: rich>=14.2.0
Requires-Dist: sh>=2.2.2
Requires-Dist: typer>=0.19.2
Requires-Python: >=3.10
Project-URL: Homepage, https://github.com/lucabello/docker-captain
Project-URL: Repository, https://github.com/lucabello/docker-captain
Project-URL: Issues, https://github.com/lucabello/docker-captain/issues
